{
    "authorCountryOfCitizenship": null,
    "authorFirstName": "Eyal",
    "authorFullName": "Eyal Weizman",
    "authorGender": null,
    "authorLastName": "Weizman",
    "averageRating": 4.45,
    "centuryOfPublication": null,
    "genres": [
        "Politics",
        "Architecture",
        "History",
        "Nonfiction",
        "Science > Geography",
        "Cultural > Israel",
        "Philosophy > Theory",
        "Cities > Urbanism",
        "Philosophy",
        "Urban"
    ],
    "goodreadsUrl": "=HYPERLINK(\"https://www.goodreads.com/book/show/1086651.Hollow_Land\", \"Goodreads URL\")",
    "isbn": 1786634481,
    "isbn13": null,
    "lists": null,
    "numberOfPages": 318,
    "numberOfRatings": 397,
    "numberOfReviews": 48,
    "numericId": 1086651,
    "primaryGenre": "Politics",
    "ratingDistribution": null,
    "seriesName": null,
    "seriesUrl": null,
    "shelves": null,
    "title": "Hollow Land: Israel's Architecture of Occupation",
    "titleId": "1086651.Hollow_Land",
    "yearOfPublication": null
}