{
    "authorCountryOfCitizenship": null,
    "authorFirstName": "John",
    "authorFullName": "John  Williams",
    "authorGender": null,
    "authorLastName": "Williams",
    "averageRating": 4.3,
    "centuryOfPublication": 20,
    "genres": [
        "Fiction",
        "Classics",
        "Literature",
        "Novels",
        "Literature > American",
        "Historical > Historical Fiction",
        "Literary Fiction",
        "The United States Of America",
        "Literature > 20th Century",
        "American > Americana"
    ],
    "goodreadsUrl": "=HYPERLINK(\"https://www.goodreads.com/book/show/166997.Stoner\", \"Goodreads URL\")",
    "isbn": 9938880398,
    "isbn13": null,
    "lists": null,
    "numberOfPages": 278,
    "numberOfRatings": 123156,
    "numberOfReviews": 13704,
    "numericId": 166997,
    "primaryGenre": "Fiction",
    "ratingDistribution": null,
    "seriesName": null,
    "seriesUrl": null,
    "shelves": null,
    "title": "Stoner",
    "titleId": "166997.Stoner",
    "yearOfPublication": 1965
}